ftpmail
