Metadata-Version: 1.0
Name: ftpmail
Version: 0.8.1
Summary: accept FTP uploads and forward via SMTP
Home-page: https://git.nerdworks.de/nerdworks/ftpmail
Author: Enno Lohmeier
Author-email: elo-pypi@nerdworks.de
License: UNKNOWN
Platform: UNKNOWN
